azure_key_vault_alert/__init__.py
azure_key_vault_alert/azure_key_vault_alert.py
azure_key_vault_alert/slack_alert.py
azure_key_vault_alert/teams_alert.py
ste_dev_01-0.0.1.dist-info/LICENSE
ste_dev_01-0.0.1.dist-info/METADATA
ste_dev_01-0.0.1.dist-info/WHEEL
ste_dev_01-0.0.1.dist-info/top_level.txt
ste_dev_01-0.0.1.dist-info/RECORD
