Metadata-Version: 2.1
Name: ste-dev-01
Version: 0.0.1
Summary: Post Key Vault Secrets report to webhook
License: MIT License
License-File: LICENSE
Requires-Dist: certifi ==2024.2.2
Requires-Dist: charset-normalizer ==3.3.2
Requires-Dist: idna ==3.6
Requires-Dist: ops-py-azure-key-vault-report ==3.1.0
Requires-Dist: ops-py-message-handler ==1.0.2
Requires-Dist: pip ==24.0
Requires-Dist: requests ==2.31.0
Requires-Dist: setuptools ==69.0.3
Requires-Dist: urllib3 ==2.2.0
Requires-Dist: wheel ==0.42.0
